sanyam_algosdk_2315/Receive_data_from_bus.py
sanyam_algosdk_2315/Send_data_to_bus.py
sanyam_algosdk_2315/__init__.py
sanyam_algosdk_2315/filter_blockchain_response.py
sanyam_algosdk_2315-0.1.3.dist-info/LICENSE
sanyam_algosdk_2315-0.1.3.dist-info/METADATA
sanyam_algosdk_2315-0.1.3.dist-info/WHEEL
sanyam_algosdk_2315-0.1.3.dist-info/top_level.txt
sanyam_algosdk_2315-0.1.3.dist-info/RECORD
